ba_az_types/AppRegistration.py
ba_az_types/AzureResources.py
ba_az_types/ContainerRegistry.py
ba_az_types/Database.py
ba_az_types/KeyVault.py
ba_az_types/RedisCache.py
ba_az_types/ResourceGroup.py
ba_az_types/StorageAccount.py
ba_az_types/StorageContainer.py
ba_az_types/StorageTable.py
ba_az_types/VarName.py
ba_az_types/WebApp.py
ba_az_types/__about__.py
ba_az_types/__init__.py
ba_az_types/interfaces/IAppRegistration.py
ba_az_types/interfaces/IAzureResources.py
ba_az_types/interfaces/ICategorizableResource.py
ba_az_types/interfaces/IContainerRegistry.py
ba_az_types/interfaces/IDatabase.py
ba_az_types/interfaces/IKeyVault.py
ba_az_types/interfaces/IRedisCache.py
ba_az_types/interfaces/IResource.py
ba_az_types/interfaces/IResourceGroup.py
ba_az_types/interfaces/IStorageAccount.py
ba_az_types/interfaces/IStorageContainer.py
ba_az_types/interfaces/IStorageTable.py
ba_az_types/interfaces/IVarName.py
ba_az_types/interfaces/IVarNameStorageContainer.py
ba_az_types/interfaces/IVarNameStorageTable.py
ba_az_types/interfaces/IWebApp.py
ba_az_types/interfaces/IWebAppAssociatedResource.py
ba_az_types-0.0.7.dist-info/METADATA
ba_az_types-0.0.7.dist-info/WHEEL
ba_az_types-0.0.7.dist-info/licenses/LICENSE
ba_az_types-0.0.7.dist-info/RECORD
