Metadata-Version: 2.1
Name: ba_az_types
Version: 0.0.7
Summary: Bridgeman Accessible's Azure types for it's infrastructure
Project-URL: Documentation, https://github.com/AlanBridgeman/BA_az_types#readme
Project-URL: Issues, https://github.com/AlanBridgeman/BA_az_types/issues
Project-URL: Source, https://github.com/AlanBridgeman/BA_az_types
Author-email: Alan Bridgeman <alan@alanbridgeman.ca>
License-Expression: MIT
License-File: LICENSE
Classifier: Development Status :: 4 - Beta
Classifier: Programming Language :: Python
Classifier: Programming Language :: Python :: 3.7
Classifier: Programming Language :: Python :: 3.8
Classifier: Programming Language :: Python :: 3.9
Classifier: Programming Language :: Python :: 3.10
Classifier: Programming Language :: Python :: 3.11
Classifier: Programming Language :: Python :: Implementation :: CPython
Classifier: Programming Language :: Python :: Implementation :: PyPy
Requires-Python: >=3.7
